<group>
<range start="2450194432" end="2450259967" country="AU" />
<range start="2452815872" end="2452881407" country="JP" />
<range start="2453143552" end="2453209087" country="JP" />
<range start="2453536768" end="2453602303" country="AU" />
<range start="2457075712" end="2457141247" country="AU" />
<range start="2457141248" end="2457206783" country="JP" />
<range start="2457206784" end="2457272319" country="AU" />
<range start="2458910720" end="2458976255" country="AU" />
<range start="2460680192" end="2460745727" country="NZ" />
<range start="2461138944" end="2461204479" country="AU" />
<range start="2462253056" end="2462318591" country="AU" />
<range start="2462318592" end="2462384127" country="AU" />
<range start="2463956992" end="2464022527" country="AU" />
<range start="2449539072" end="2449604607" country="US" />
<range start="2449801216" end="2449866751" country="US" />
<range start="2449866752" end="2449932287" country="US" />
<range start="2449932288" end="2449997823" country="US" />
<range start="2449997824" end="2450063359" country="US" />
<range start="2450063360" end="2450128895" country="US" />
<range start="2450128896" end="2450194431" country="US" />
<range start="2450259968" end="2450325503" country="US" />
<range start="2450325504" end="2450391039" country="US" />
<range start="2450391040" end="2450456575" country="US" />
<range start="2450456576" end="2450522111" country="US" />
<range start="2450522112" end="2450587647" country="US" />
<range start="2450587648" end="2450653183" country="US" />
<range start="2450653184" end="2450718719" country="US" />
<range start="2450784256" end="2450849791" country="US" />
<range start="2450915328" end="2452553727" country="US" />
<range start="2452553728" end="2452619263" country="US" />
<range start="2452684800" end="2452750335" country="US" />
<range start="2452946944" end="2453012479" country="US" />
<range start="2453012480" end="2453078015" country="US" />
<range start="2453078016" end="2453143551" country="US" />
<range start="2453209088" end="2453274623" country="US" />
<range start="2453274624" end="2453340159" country="US" />
<range start="2453471232" end="2453536767" country="US" />
<range start="2453602304" end="2453667839" country="US" />
<range start="2453733376" end="2453798911" country="US" />
<range start="2453929984" end="2453995519" country="US" />
<range start="2453995520" end="2454061055" country="US" />
<range start="2454126592" end="2454192127" country="US" />
<range start="2454257664" end="2454323199" country="US" />
<range start="2454323200" end="2454388735" country="US" />
<range start="2454454272" end="2454519807" country="US" />
<range start="2454585344" end="2454650879" country="US" />
<range start="2454650880" end="2454716415" country="US" />
<range start="2454847488" end="2454913023" country="US" />
<range start="2454978560" end="2455044095" country="US" />
<range start="2455044096" end="2455109631" country="US" />
<range start="2455109632" end="2455175167" country="US" />
<range start="2455240704" end="2455306239" country="US" />
<range start="2455306240" end="2455371775" country="US" />
<range start="2455437312" end="2455502847" country="US" />
<range start="2455502848" end="2455568383" country="US" />
<range start="2455568384" end="2455633919" country="US" />
<range start="2455633920" end="2455699455" country="US" />
<range start="2455699456" end="2455764991" country="US" />
<range start="2455764992" end="2455830527" country="US" />
<range start="2455896064" end="2455961599" country="US" />
<range start="2455961600" end="2456027135" country="US" />
<range start="2456748032" end="2456813567" country="US" />
<range start="2456879104" end="2456944639" country="US" />
<range start="2456944640" end="2457010175" country="US" />
<range start="2457010176" end="2457075711" country="US" />
<range start="2457403392" end="2457468927" country="US" />
<range start="2457468928" end="2457534463" country="US" />
<range start="2457534464" end="2457599999" country="US" />
<range start="2457665536" end="2457731071" country="US" />
<range start="2457731072" end="2457796607" country="US" />
<range start="2457796608" end="2457862143" country="US" />
<range start="2457862144" end="2457927679" country="US" />
<range start="2457927680" end="2457993215" country="US" />
<range start="2457993216" end="2458058751" country="US" />
<range start="2458058752" end="2458124287" country="CA" />
<range start="2458124288" end="2458189823" country="US" />
<range start="2458320896" end="2458353663" country="US" />
<range start="2458353664" end="2458386431" country="US" />
<range start="2458451968" end="2458517503" country="US" />
<range start="2458517504" end="2458583039" country="US" />
<range start="2458583040" end="2458648575" country="US" />
<range start="2458779648" end="2458845183" country="US" />
<range start="2458845184" end="2458910719" country="US" />
<range start="2458976256" end="2459041791" country="US" />
<range start="2459041792" end="2459107327" country="US" />
<range start="2459107328" end="2459172863" country="US" />
<range start="2459172864" end="2459238399" country="US" />
<range start="2459238400" end="2459303935" country="US" />
<range start="2459303936" end="2459369471" country="US" />
<range start="2459369472" end="2459435007" country="US" />
<range start="2459435008" end="2459500543" country="US" />
<range start="2459500544" end="2459566079" country="US" />
<range start="2459566080" end="2459631615" country="US" />
<range start="2459697152" end="2459762687" country="US" />
<range start="2459762688" end="2459828223" country="US" />
<range start="2459959296" end="2460024831" country="US" />
<range start="2460155904" end="2460221439" country="US" />
<range start="2460286976" end="2460352511" country="US" />
<range start="2460352512" end="2460418047" country="US" />
<range start="2460418048" end="2460483583" country="US" />
<range start="2460483584" end="2460549119" country="US" />
<range start="2460614656" end="2460680191" country="US" />
<range start="2460876800" end="2460942335" country="US" />
<range start="2461270016" end="2461335551" country="US" />
<range start="2461335552" end="2461401087" country="US" />
<range start="2461466624" end="2461532159" country="US" />
<range start="2461532160" end="2461597695" country="US" />
<range start="2461663232" end="2461728767" country="US" />
<range start="2461728768" end="2461794303" country="US" />
<range start="2461859840" end="2461925375" country="US" />
<range start="2461925376" end="2461990911" country="US" />
<range start="2462384128" end="2462449663" country="US" />
<range start="2462449664" end="2462515199" country="US" />
<range start="2462515200" end="2462580735" country="US" />
<range start="2462580736" end="2462646271" country="US" />
<range start="2462646272" end="2462711807" country="US" />
<range start="2462711808" end="2462777343" country="US" />
<range start="2462777344" end="2462842879" country="US" />
<range start="2462842880" end="2463105023" country="US" />
<range start="2463105024" end="2463170559" country="US" />
<range start="2463170560" end="2463236095" country="US" />
<range start="2463498240" end="2463563775" country="US" />
<range start="2463563776" end="2463629311" country="US" />
<range start="2463694848" end="2463760383" country="US" />
<range start="2463760384" end="2463825919" country="US" />
<range start="2464022528" end="2464088063" country="US" />
<range start="2464088064" end="2464153599" country="US" />
<range start="2464219136" end="2464284671" country="US" />
<range start="2464284672" end="2464350207" country="VI" />
<range start="2464481280" end="2464546815" country="US" />
<range start="2464743424" end="2464808959" country="US" />
<range start="2464874496" end="2464940031" country="US" />
<range start="2464940032" end="2465005567" country="US" />
<range start="2465005568" end="2465071103" country="US" />
<range start="2465071104" end="2465136639" country="US" />
<range start="2465136640" end="2465202175" country="US" />
<range start="2465202176" end="2465267711" country="US" />
<range start="2465267712" end="2465333247" country="US" />
<range start="2465333248" end="2465398783" country="US" />
<range start="2465398784" end="2465464319" country="US" />
<range start="2465464320" end="2465529855" country="US" />
<range start="2465529856" end="2465595391" country="US" />
<range start="2465595392" end="2465660927" country="US" />
<range start="2465857536" end="2465923071" country="US" />
<range start="2465988608" end="2466054143" country="US" />
<range start="2454913024" end="2454978559" country="CL" />
<range start="2458255360" end="2458320895" country="BR" />
<range start="2459631616" end="2459697151" country="CL" />
<range start="2460221440" end="2460286975" country="BR" />
<range start="2449604608" end="2449670143" country="EU" />
<range start="2449670144" end="2449735679" country="EU" />
<range start="2449735680" end="2449801215" country="EU" />
<range start="2450718720" end="2450784255" country="EU" />
<range start="2452619264" end="2452684799" country="IT" />
<range start="2452750336" end="2452815871" country="EU" />
<range start="2453340160" end="2453405695" country="EU" />
<range start="2453864448" end="2453929983" country="EU" />
<range start="2454061056" end="2454126591" country="EU" />
<range start="2454192128" end="2454257663" country="EU" />
<range start="2454388736" end="2454454271" country="EU" />
<range start="2454716416" end="2454781951" country="EU" />
<range start="2454781952" end="2454847487" country="EU" />
<range start="2455175168" end="2455240703" country="EU" />
<range start="2455830528" end="2455896063" country="EU" />
<range start="2456027136" end="2456092671" country="EU" />
<range start="2456092672" end="2456158207" country="EU" />
<range start="2456158208" end="2456223743" country="EU" />
<range start="2456223744" end="2456289279" country="EU" />
<range start="2456354816" end="2456420351" country="EU" />
<range start="2456420352" end="2456485887" country="EU" />
<range start="2456485888" end="2456551423" country="EU" />
<range start="2456551424" end="2456616959" country="AT" />
<range start="2456616960" end="2456682495" country="EU" />
<range start="2456682496" end="2456748031" country="EU" />
<range start="2456813568" end="2456879103" country="EU" />
<range start="2457272320" end="2457337855" country="EU" />
<range start="2457600000" end="2457665535" country="EU" />
<range start="2458189824" end="2458255359" country="EU" />
<range start="2458386432" end="2458451967" country="EU" />
<range start="2458648576" end="2458714111" country="EU" />
<range start="2459893760" end="2459959295" country="EU" />
<range start="2460024832" end="2460090367" country="EU" />
<range start="2460090368" end="2460155903" country="EU" />
<range start="2460549120" end="2460614655" country="EU" />
<range start="2460745728" end="2460811263" country="NO" />
<range start="2460811264" end="2460876799" country="EU" />
<range start="2460942336" end="2461007871" country="EU" />
<range start="2461007872" end="2461073407" country="EU" />
<range start="2461204480" end="2461270015" country="EU" />
<range start="2461794304" end="2461859839" country="EU" />
<range start="2461990912" end="2462056447" country="EU" />
<range start="2462056448" end="2462121983" country="EU" />
<range start="2462121984" end="2462187519" country="EU" />
<range start="2463236096" end="2463301631" country="EU" />
<range start="2463301632" end="2463367167" country="EU" />
<range start="2463432704" end="2463498239" country="EU" />
<range start="2463629312" end="2463694847" country="EU" />
<range start="2463825920" end="2463891455" country="EU" />
<range start="2463891456" end="2463956991" country="EU" />
<range start="2464153600" end="2464219135" country="EU" />
<range start="2464350208" end="2464415743" country="EU" />
<range start="2464415744" end="2464481279" country="EU" />
<range start="2464808960" end="2464874495" country="EU" />
<range start="2465726464" end="2465791999" country="EU" />
<range start="2465792000" end="2465857535" country="EU" />
<range start="2466054144" end="2466119679" country="EU" />
<range start="2466119680" end="2466185215" country="EU" />
<range start="2453667840" end="2453733375" country="ZA" />
<range start="2458714112" end="2458779647" country="ZA" />
<range start="2461401088" end="2461466623" country="ZA" />
<range start="2464546816" end="2464612351" country="ZA" />
<range start="2464612352" end="2464677887" country="ZA" />
<range start="2464677888" end="2464743423" country="ZA" />
</group>
