<group>
<range start="2653421568" end="2653487103" country="AU" />
<range start="2653683712" end="2653749247" country="KR" />
<range start="2653749248" end="2653814783" country="AU" />
<range start="2654339072" end="2654404607" country="AU" />
<range start="2656632832" end="2656698367" country="AU" />
<range start="2657878016" end="2657943551" country="TH" />
<range start="2659450880" end="2659516415" country="HK" />
<range start="2660237312" end="2660302847" country="IN" />
<range start="2661351424" end="2661416959" country="BN" />
<range start="2662727680" end="2662793215" country="HK" />
<range start="2663776256" end="2663841791" country="JP" />
<range start="2663841792" end="2663907327" country="JP" />
<range start="2663907328" end="2663972863" country="JP" />
<range start="2663972864" end="2664038399" country="JP" />
<range start="2664038400" end="2664103935" country="JP" />
<range start="2664103936" end="2664169471" country="JP" />
<range start="2664169472" end="2664235007" country="JP" />
<range start="2664235008" end="2664300543" country="JP" />
<range start="2664300544" end="2664366079" country="JP" />
<range start="2664366080" end="2664431615" country="JP" />
<range start="2664431616" end="2664497151" country="JP" />
<range start="2664497152" end="2664562687" country="JP" />
<range start="2664562688" end="2664628223" country="JP" />
<range start="2664628224" end="2664693759" country="JP" />
<range start="2664693760" end="2664759295" country="JP" />
<range start="2664759296" end="2664824831" country="JP" />
<range start="2664824832" end="2664890367" country="JP" />
<range start="2664890368" end="2664955903" country="JP" />
<range start="2664955904" end="2665021439" country="JP" />
<range start="2665021440" end="2665086975" country="JP" />
<range start="2650865664" end="2650931199" country="US" />
<range start="2650931200" end="2650996735" country="US" />
<range start="2650996736" end="2651062271" country="US" />
<range start="2651062272" end="2651127807" country="US" />
<range start="2651127808" end="2651193343" country="US" />
<range start="2651193344" end="2651258879" country="US" />
<range start="2651258880" end="2651324415" country="US" />
<range start="2651324416" end="2651389951" country="US" />
<range start="2651389952" end="2651455487" country="US" />
<range start="2651455488" end="2651521023" country="US" />
<range start="2651521024" end="2651586559" country="US" />
<range start="2651586560" end="2651652095" country="US" />
<range start="2651652096" end="2651717631" country="US" />
<range start="2651717632" end="2651783167" country="US" />
<range start="2651783168" end="2651848703" country="US" />
<range start="2651848704" end="2651914239" country="US" />
<range start="2651914240" end="2651979775" country="US" />
<range start="2651979776" end="2652045311" country="US" />
<range start="2652045312" end="2652110847" country="US" />
<range start="2652110848" end="2652176383" country="US" />
<range start="2652176384" end="2652241919" country="US" />
<range start="2652241920" end="2652307455" country="US" />
<range start="2652307456" end="2652372991" country="US" />
<range start="2652372992" end="2652438527" country="US" />
<range start="2652438528" end="2652504063" country="US" />
<range start="2652504064" end="2652569599" country="US" />
<range start="2652569600" end="2652635135" country="US" />
<range start="2652635136" end="2652700671" country="US" />
<range start="2652700672" end="2652766207" country="US" />
<range start="2652766208" end="2652831743" country="US" />
<range start="2652831744" end="2652897279" country="US" />
<range start="2652897280" end="2652962815" country="US" />
<range start="2652962816" end="2653028351" country="US" />
<range start="2653028352" end="2653093887" country="US" />
<range start="2653093888" end="2653159423" country="US" />
<range start="2653945856" end="2654011391" country="US" />
<range start="2654142464" end="2654207999" country="CA" />
<range start="2654208000" end="2654273535" country="US" />
<range start="2654273536" end="2654339071" country="US" />
<range start="2654404608" end="2654470143" country="US" />
<range start="2654470144" end="2654535679" country="US" />
<range start="2654535680" end="2654601215" country="US" />
<range start="2654666752" end="2654732287" country="US" />
<range start="2654732288" end="2654797823" country="US" />
<range start="2654797824" end="2654863359" country="US" />
<range start="2654863360" end="2654928895" country="US" />
<range start="2654928896" end="2654994431" country="US" />
<range start="2655059968" end="2655125503" country="US" />
<range start="2655256576" end="2655322111" country="US" />
<range start="2655322112" end="2655387647" country="US" />
<range start="2655387648" end="2655453183" country="US" />
<range start="2655453184" end="2655518719" country="US" />
<range start="2655518720" end="2655584255" country="US" />
<range start="2655584256" end="2655649791" country="US" />
<range start="2655649792" end="2655715327" country="US" />
<range start="2655780864" end="2655846399" country="US" />
<range start="2655846400" end="2655911935" country="US" />
<range start="2655911936" end="2655977471" country="US" />
<range start="2655977472" end="2656043007" country="US" />
<range start="2656043008" end="2656108543" country="US" />
<range start="2656108544" end="2656141311" country="US" />
<range start="2656141312" end="2656174079" country="US" />
<range start="2656174080" end="2656239615" country="US" />
<range start="2656239616" end="2656305151" country="US" />
<range start="2656305152" end="2656370687" country="US" />
<range start="2656370688" end="2656436223" country="US" />
<range start="2656436224" end="2656501759" country="US" />
<range start="2656501760" end="2656567295" country="US" />
<range start="2656567296" end="2656632831" country="US" />
<range start="2656763904" end="2656829439" country="US" />
<range start="2656894976" end="2656960511" country="US" />
<range start="2657026048" end="2657091583" country="US" />
<range start="2657091584" end="2657157119" country="US" />
<range start="2657222656" end="2657288191" country="US" />
<range start="2657353728" end="2657419263" country="US" />
<range start="2657419264" end="2657484799" country="US" />
<range start="2657550336" end="2657615871" country="US" />
<range start="2657615872" end="2657681407" country="US" />
<range start="2657746944" end="2657812479" country="US" />
<range start="2657812480" end="2657878015" country="US" />
<range start="2658074624" end="2658140159" country="US" />
<range start="2658205696" end="2658271231" country="US" />
<range start="2658271232" end="2658336767" country="US" />
<range start="2658336768" end="2658402303" country="US" />
<range start="2658402304" end="2658467839" country="US" />
<range start="2658467840" end="2658533375" country="US" />
<range start="2658533376" end="2658598911" country="US" />
<range start="2658664448" end="2658729983" country="US" />
<range start="2658729984" end="2658795519" country="US" />
<range start="2658795520" end="2658861055" country="US" />
<range start="2658861056" end="2658926591" country="US" />
<range start="2659188736" end="2659254271" country="CA" />
<range start="2659319808" end="2659385343" country="US" />
<range start="2659581952" end="2659647487" country="US" />
<range start="2659647488" end="2659713023" country="US" />
<range start="2659713024" end="2659778559" country="US" />
<range start="2659778560" end="2659844095" country="US" />
<range start="2659844096" end="2659909631" country="US" />
<range start="2659909632" end="2659975167" country="US" />
<range start="2659975168" end="2660040703" country="US" />
<range start="2660040704" end="2660106239" country="CA" />
<range start="2660106240" end="2660171775" country="US" />
<range start="2660302848" end="2660368383" country="US" />
<range start="2660368384" end="2660433919" country="US" />
<range start="2660433920" end="2660499455" country="US" />
<range start="2660696064" end="2660761599" country="US" />
<range start="2660827136" end="2660892671" country="US" />
<range start="2660892672" end="2660958207" country="US" />
<range start="2660958208" end="2661023743" country="US" />
<range start="2661089280" end="2661154815" country="US" />
<range start="2661154816" end="2661220351" country="US" />
<range start="2661220352" end="2661285887" country="US" />
<range start="2661482496" end="2661548031" country="CA" />
<range start="2661548032" end="2661613567" country="US" />
<range start="2661613568" end="2661679103" country="US" />
<range start="2662006784" end="2662072319" country="US" />
<range start="2662793216" end="2662858751" country="US" />
<range start="2662858752" end="2662924287" country="US" />
<range start="2662924288" end="2662989823" country="US" />
<range start="2662989824" end="2663055359" country="US" />
<range start="2663055360" end="2663120895" country="US" />
<range start="2663120896" end="2663186431" country="US" />
<range start="2663186432" end="2663251967" country="US" />
<range start="2665152512" end="2665218047" country="US" />
<range start="2665283584" end="2665349119" country="US" />
<range start="2665349120" end="2665414655" country="US" />
<range start="2665480192" end="2665545727" country="US" />
<range start="2665742336" end="2665807871" country="US" />
<range start="2665807872" end="2665873407" country="US" />
<range start="2666201088" end="2666266623" country="US" />
<range start="2666266624" end="2666332159" country="US" />
<range start="2666332160" end="2666397695" country="US" />
<range start="2666397696" end="2666463231" country="US" />
<range start="2666463232" end="2666528767" country="US" />
<range start="2666528768" end="2666594303" country="US" />
<range start="2666594304" end="2666659839" country="US" />
<range start="2666659840" end="2666725375" country="US" />
<range start="2666725376" end="2666790911" country="US" />
<range start="2666790912" end="2666856447" country="US" />
<range start="2666856448" end="2666921983" country="US" />
<range start="2666921984" end="2666987519" country="US" />
<range start="2666987520" end="2667053055" country="US" />
<range start="2667315200" end="2667380735" country="US" />
<range start="2667380736" end="2667446271" country="US" />
<range start="2667446272" end="2667511807" country="US" />
<range start="2657157120" end="2657222655" country="MX" />
<range start="2661285888" end="2661351423" country="VE" />
<range start="2661941248" end="2662006783" country="CL" />
<range start="2667249664" end="2667315199" country="CL" />
<range start="2653159424" end="2653224959" country="EU" />
<range start="2653224960" end="2653290495" country="EU" />
<range start="2653290496" end="2653356031" country="EU" />
<range start="2653356032" end="2653421567" country="EU" />
<range start="2653487104" end="2653552639" country="EU" />
<range start="2653552640" end="2653618175" country="EU" />
<range start="2653618176" end="2653683711" country="GB" />
<range start="2653880320" end="2653945855" country="EU" />
<range start="2654011392" end="2654076927" country="EU" />
<range start="2654076928" end="2654142463" country="EU" />
<range start="2654994432" end="2655059967" country="EU" />
<range start="2655125504" end="2655191039" country="EU" />
<range start="2655715328" end="2655780863" country="EU" />
<range start="2656698368" end="2656763903" country="EU" />
<range start="2656829440" end="2656894975" country="EU" />
<range start="2656960512" end="2657026047" country="EU" />
<range start="2657288192" end="2657353727" country="EU" />
<range start="2657484800" end="2657550335" country="EU" />
<range start="2657681408" end="2657746943" country="EU" />
<range start="2657943552" end="2658009087" country="EU" />
<range start="2658009088" end="2658074623" country="EU" />
<range start="2658140160" end="2658205695" country="EU" />
<range start="2658598912" end="2658664447" country="EU" />
<range start="2658926592" end="2658992127" country="EU" />
<range start="2658992128" end="2659057663" country="EU" />
<range start="2659057664" end="2659123199" country="EU" />
<range start="2659254272" end="2659319807" country="EU" />
<range start="2659385344" end="2659450879" country="EU" />
<range start="2659516416" end="2659581951" country="EU" />
<range start="2660171776" end="2660237311" country="EU" />
<range start="2660761600" end="2660827135" country="GB" />
<range start="2661023744" end="2661089279" country="EU" />
<range start="2661416960" end="2661482495" country="EU" />
<range start="2661679104" end="2661744639" country="EU" />
<range start="2661744640" end="2661810175" country="EU" />
<range start="2661810176" end="2661875711" country="EU" />
<range start="2661875712" end="2661941247" country="EU" />
<range start="2662203392" end="2662268927" country="EU" />
<range start="2662268928" end="2662334463" country="EU" />
<range start="2662334464" end="2662399999" country="EU" />
<range start="2662400000" end="2662465535" country="EU" />
<range start="2662465536" end="2662531071" country="EU" />
<range start="2662531072" end="2662596607" country="EU" />
<range start="2662596608" end="2662662143" country="EU" />
<range start="2663251968" end="2663317503" country="EU" />
<range start="2663317504" end="2663383039" country="EU" />
<range start="2663383040" end="2663448575" country="EU" />
<range start="2663448576" end="2663514111" country="EU" />
<range start="2663514112" end="2663579647" country="EU" />
<range start="2663579648" end="2663645183" country="EU" />
<range start="2663645184" end="2663710719" country="EU" />
<range start="2663710720" end="2663776255" country="EU" />
<range start="2665086976" end="2665152511" country="EU" />
<range start="2665218048" end="2665283583" country="EU" />
<range start="2665414656" end="2665480191" country="EU" />
<range start="2665545728" end="2665611263" country="EU" />
<range start="2665611264" end="2665676799" country="EU" />
<range start="2665676800" end="2665742335" country="EU" />
<range start="2665873408" end="2665938943" country="EU" />
<range start="2665938944" end="2666004479" country="EU" />
<range start="2666004480" end="2666070015" country="CH" />
<range start="2666135552" end="2666201087" country="EU" />
<range start="2667184128" end="2667249663" country="EU" />
</group>
