<group>
<range start="2854617088" end="2854682623" country="MY" />
<range start="2858352640" end="2858418175" country="SG" />
<range start="2862415872" end="2862481407" country="AU" />
<range start="2863857664" end="2863923199" country="SG" />
<range start="2852192256" end="2853306367" country="US" />
<range start="2853371904" end="2853765119" country="US" />
<range start="2853830656" end="2854617087" country="US" />
<range start="2854682624" end="2855469055" country="US" />
<range start="2855534592" end="2856058879" country="US" />
<range start="2856124416" end="2856452095" country="US" />
<range start="2856517632" end="2856714239" country="US" />
<range start="2856779776" end="2857238527" country="US" />
<range start="2857697280" end="2858352639" country="US" />
<range start="2858418176" end="2861957119" country="US" />
<range start="2862022656" end="2862284799" country="US" />
<range start="2862350336" end="2862415871" country="US" />
<range start="2862481408" end="2863202303" country="US" />
<range start="2863267840" end="2863595519" country="US" />
<range start="2863595520" end="2863661055" country="CA" />
<range start="2863661056" end="2863857663" country="US" />
<range start="2863923200" end="2865889279" country="US" />
<range start="2865954816" end="2867396607" country="US" />
<range start="2867462144" end="2867593215" country="US" />
<range start="2867855360" end="2868117503" country="US" />
<range start="2868379648" end="2868772863" country="US" />
<range start="2853306368" end="2853371903" country="CL" />
<range start="2853765120" end="2853830655" country="MX" />
<range start="2855469056" end="2855534591" country="AR" />
<range start="2856452096" end="2856517631" country="BR" />
<range start="2856714240" end="2856779775" country="MX" />
<range start="2862284800" end="2862350335" country="AR" />
<range start="2863202304" end="2863267839" country="MX" />
<range start="2865889280" end="2865954815" country="AR" />
<range start="2856058880" end="2856124415" country="EU" />
<range start="2867593216" end="2867724287" country="EU" />
<range start="2868838400" end="2868903935" country="EU" />
</group>
