<group>
<range start="3523215360" end="3523223551" country="AU" />
<range start="3523223552" end="3523231743" country="KR" />
<range start="3523231744" end="3523248127" country="AU" />
<range start="3523248128" end="3523280895" country="HK" />
<range start="3523280896" end="3523297279" country="TH" />
<range start="3523297280" end="3523317759" country="PH" />
<range start="3523317760" end="3523330047" country="JP" />
<range start="3523330048" end="3523338239" country="AU" />
<range start="3523338240" end="3523342335" country="LK" />
<range start="3523342336" end="3523346431" country="HK" />
<range start="3523346432" end="3523354623" country="CN" />
<range start="3523354624" end="3523362815" country="KR" />
<range start="3523362816" end="3523379199" country="JP" />
<range start="3523379200" end="3523395583" country="PK" />
<range start="3523395584" end="3523411967" country="JP" />
<range start="3523411968" end="3523477503" country="HK" />
<range start="3523477504" end="3523493887" country="PH" />
<range start="3523493888" end="3523497983" country="BD" />
<range start="3523497984" end="3523500031" country="AU" />
<range start="3523502080" end="3523510271" country="PH" />
<range start="3523510272" end="3523518463" country="TH" />
<range start="3523518464" end="3523526655" country="JP" />
<range start="3523526656" end="3523530751" country="AP" />
<range start="3523530752" end="3523532799" country="NZ" />
<range start="3523534848" end="3523538943" country="AU" />
<range start="3523543040" end="3523551231" country="CN" />
<range start="3523551232" end="3523553279" country="AU" />
<range start="3523555328" end="3523557375" country="NZ" />
<range start="3523559424" end="3523575807" country="PH" />
<range start="3523579904" end="3523583999" country="CN" />
<range start="3523584000" end="3523592191" country="HK" />
<range start="3523592192" end="3523608575" country="AP" />
<range start="3523608576" end="3523674111" country="HK" />
<range start="3523674112" end="3523682303" country="FJ" />
<range start="3523682304" end="3523686399" country="NZ" />
<range start="3523690496" end="3523698687" country="IN" />
<range start="3523698688" end="3523739647" country="AP" />
<range start="3523739648" end="3524001791" country="AU" />
<range start="3524001792" end="3524132863" country="CN" />
<range start="3524132864" end="3524145151" country="PH" />
<range start="3524145152" end="3524149247" country="JP" />
<range start="3524149248" end="3524157439" country="CN" />
<range start="3524157440" end="3524161535" country="AU" />
<range start="3524165632" end="3524247551" country="CN" />
<range start="3524247552" end="3524263935" country="AU" />
<range start="3524263936" end="3524296703" country="PH" />
<range start="3524296704" end="3524313087" country="CN" />
<range start="3524313088" end="3524329471" country="KR" />
<range start="3524329472" end="3524362239" country="TW" />
<range start="3524362240" end="3524395007" country="HK" />
<range start="3524395008" end="3524444159" country="IN" />
<range start="3524444160" end="3524460543" country="AU" />
<range start="3524460544" end="3524526079" country="MY" />
<range start="3524526080" end="3524591615" country="JP" />
<range start="3524591616" end="3524722687" country="CN" />
<range start="3524722688" end="3524730879" country="SG" />
<range start="3524730880" end="3524739071" country="CN" />
<range start="3524739072" end="3524743167" country="ID" />
<range start="3524743168" end="3524747263" country="MP" />
<range start="3524747264" end="3524755455" country="PH" />
<range start="3524755456" end="3524763647" country="SG" />
<range start="3524763648" end="3524788223" country="PH" />
<range start="3524788224" end="3524853759" country="SG" />
<range start="3524853760" end="3526361087" country="CN" />
<range start="3526361088" end="3526393855" country="NZ" />
<range start="3526393856" end="3526395903" country="JP" />
<range start="3526397952" end="3526402047" country="MY" />
<range start="3526402048" end="3526410239" country="NZ" />
<range start="3526410240" end="3526414335" country="MY" />
<range start="3526414336" end="3526416383" country="AU" />
<range start="3526418432" end="3526426623" country="JP" />
<range start="3526426624" end="3526557695" country="AU" />
<range start="3526557696" end="3526754303" country="CN" />
<range start="3526754304" end="3526885375" country="NZ" />
<range start="3526885376" end="3526893567" country="PK" />
<range start="3526893568" end="3526897663" country="NZ" />
<range start="3526897664" end="3526901759" country="HK" />
<range start="3526901760" end="3526909951" country="AU" />
<range start="3526909952" end="3526918143" country="IN" />
<range start="3526918144" end="3526922239" country="SG" />
<range start="3526922240" end="3526924287" country="BD" />
<range start="3526924288" end="3526926335" country="AU" />
<range start="3526926336" end="3526934527" country="JP" />
<range start="3526934528" end="3526942719" country="CN" />
<range start="3526942720" end="3526950911" country="AU" />
<range start="3526950912" end="3527004159" country="HK" />
<range start="3527004160" end="3527008255" country="ID" />
<range start="3527008256" end="3527016447" country="KR" />
<range start="3527016448" end="3527933951" country="TW" />
<range start="3527933952" end="3528392703" country="CN" />
<range start="3528392704" end="3528396799" country="JP" />
<range start="3528396800" end="3528400895" country="AU" />
<range start="3528400896" end="3528404991" country="JP" />
<range start="3528409088" end="3528425471" country="CN" />
<range start="3528425472" end="3528445951" country="JP" />
<range start="3528450048" end="3528458239" country="CN" />
<range start="3528458240" end="3528474623" country="AF" />
<range start="3528474624" end="3528482815" country="TW" />
<range start="3528482816" end="3528491007" country="KR" />
<range start="3528491008" end="3528507391" country="AU" />
<range start="3528507392" end="3528589311" country="JP" />
<range start="3528589312" end="3528720383" country="CN" />
<range start="3528720384" end="3528785919" country="AU" />
<range start="3528785920" end="3528851455" country="TW" />
<range start="3528851456" end="3528884223" country="NZ" />
<range start="3528884224" end="3528908799" country="TH" />
<range start="3528908800" end="3528912895" country="VN" />
<range start="3528916992" end="3528933375" country="AU" />
<range start="3528933376" end="3528949759" country="JP" />
<range start="3528949760" end="3528966143" country="CN" />
<range start="3528966144" end="3528974335" country="KR" />
<range start="3528974336" end="3528978431" country="JP" />
<range start="3528978432" end="3528982527" country="HK" />
<range start="3528982528" end="3529056255" country="JP" />
<range start="3529056256" end="3529064447" country="IN" />
<range start="3529064448" end="3529072639" country="HK" />
<range start="3529072640" end="3529080831" country="JP" />
<range start="3529080832" end="3529089023" country="AU" />
<range start="3529089024" end="3529097215" country="KR" />
<range start="3529097216" end="3529113599" country="JP" />
<range start="3529113600" end="3531603967" country="KR" />
<range start="3531603968" end="3534749695" country="JP" />
<range start="3534749696" end="3534880767" country="HK" />
<range start="3534880768" end="3535273983" country="KR" />
<range start="3535273984" end="3535339519" country="HK" />
<range start="3535339520" end="3535355903" country="NZ" />
<range start="3535355904" end="3535372287" country="AU" />
<range start="3535372288" end="3535380479" country="JP" />
<range start="3535380480" end="3535388671" country="PH" />
<range start="3535388672" end="3535405055" country="CN" />
<range start="3535405056" end="3535536127" country="MY" />
<range start="3535536128" end="3535798271" country="JP" />
<range start="3535798272" end="3535814655" country="TW" />
<range start="3535814656" end="3535822847" country="KR" />
<range start="3535822848" end="3535831039" country="CN" />
<range start="3535831040" end="3535863807" country="TW" />
<range start="3535863808" end="3535880191" country="SG" />
<range start="3535880192" end="3535896575" country="JP" />
<range start="3535896576" end="3535929343" country="AU" />
<range start="3535929344" end="3535994879" country="JP" />
<range start="3535994880" end="3536060415" country="MY" />
<range start="3536060416" end="3536322559" country="JP" />
<range start="3536322560" end="3536551935" country="TW" />
<range start="3536551936" end="3536568319" country="TH" />
<range start="3536568320" end="3536584703" country="JP" />
<range start="3536584704" end="3536846847" country="KR" />
<range start="3536846848" end="3536928767" country="TW" />
<range start="3536928768" end="3536945151" country="HK" />
<range start="3536945152" end="3536977919" country="TW" />
<range start="3536977920" end="3537010687" country="IN" />
<range start="3537010688" end="3537027071" country="ID" />
<range start="3537027072" end="3537043455" country="KR" />
<range start="3537047552" end="3537049599" country="ID" />
<range start="3537051648" end="3537055743" country="JP" />
<range start="3537059840" end="3537076223" country="AU" />
<range start="3537076224" end="3537174527" country="IN" />
<range start="3537174528" end="3537190911" country="TH" />
<range start="3537190912" end="3537240063" country="PH" />
<range start="3537240064" end="3537305599" country="IN" />
<range start="3537305600" end="3537371135" country="AU" />
<range start="3537371136" end="3537895423" country="KR" />
<range start="3537895424" end="3538943999" country="JP" />
<range start="3538944000" end="3539271679" country="TW" />
<range start="3539271680" end="3539304447" country="VN" />
<range start="3539304448" end="3539337215" country="HK" />
<range start="3539337216" end="3539353599" country="NZ" />
<range start="3539353600" end="3539402751" country="TH" />
<range start="3539402752" end="3539435519" country="JP" />
<range start="3539435520" end="3539455999" country="AU" />
<range start="3539468288" end="3539992575" country="JP" />
</group>
